demomgr/__init__.py
demomgr/__main__.py
demomgr/config.py
demomgr/constants.py
demomgr/context_menus.py
demomgr/demo_data_manager.py
demomgr/demo_info.py
demomgr/explorer.py
demomgr/filterlogic.py
demomgr/handle_events.py
demomgr/helpers.py
demomgr/main_app.py
demomgr/platforming.py
demomgr/style_helper.py
demomgr/threadgroup.py
demomgr/dialogues/__init__.py
demomgr/dialogues/_base.py
demomgr/dialogues/_diagresult.py
demomgr/dialogues/bookmark_setter.py
demomgr/dialogues/bulk_operator.py
demomgr/dialogues/cfg_error.py
demomgr/dialogues/first_run.py
demomgr/dialogues/play.py
demomgr/dialogues/settings.py
demomgr/threads/__init__.py
demomgr/threads/_base.py
demomgr/threads/_threadsig.py
demomgr/threads/cmd_demos.py
demomgr/threads/filter.py
demomgr/threads/mark_demo.py
demomgr/threads/rcon.py
demomgr/threads/read_demo_meta.py
demomgr/threads/read_folder.py
demomgr/tk_widgets/__init__.py
demomgr/tk_widgets/headed_frame.py
demomgr/tk_widgets/key_value_display.py
demomgr/tk_widgets/misc.py
demomgr/tk_widgets/ttk_text.py
demomgr/ui_themes/__init__.py
demomgr/ui_themes/dark.tcl
demomgr/ui_themes/icon.gif
demomgr/ui_themes/dark/adf.png
demomgr/ui_themes/dark/arrow-down-a.png
demomgr/ui_themes/dark/arrow-down-p.png
demomgr/ui_themes/dark/arrow-down.png
demomgr/ui_themes/dark/arrow-left-a.png
demomgr/ui_themes/dark/arrow-left-p.png
demomgr/ui_themes/dark/arrow-left.png
demomgr/ui_themes/dark/arrow-right-a.png
demomgr/ui_themes/dark/arrow-right-p.png
demomgr/ui_themes/dark/arrow-right.png
demomgr/ui_themes/dark/arrow-up-a.png
demomgr/ui_themes/dark/arrow-up-p.png
demomgr/ui_themes/dark/arrow-up.png
demomgr/ui_themes/dark/button.png
demomgr/ui_themes/dark/button_active.png
demomgr/ui_themes/dark/button_focus.png
demomgr/ui_themes/dark/button_pressed.png
demomgr/ui_themes/dark/checkbtn-n-a.png
demomgr/ui_themes/dark/checkbtn-n-f.png
demomgr/ui_themes/dark/checkbtn-n.png
demomgr/ui_themes/dark/checkbtn-s-a.png
demomgr/ui_themes/dark/checkbtn-s-f.png
Demomgr-1.11.1.dist-info/LICENSE
Demomgr-1.11.1.dist-info/METADATA
Demomgr-1.11.1.dist-info/WHEEL
Demomgr-1.11.1.dist-info/entry_points.txt
Demomgr-1.11.1.dist-info/top_level.txt
Demomgr-1.11.1.dist-info/RECORD
