Metadata-Version: 2.1
Name: Demomgr
Version: 1.11.1
Summary: TF2 demo file management tool written in Python and Tcl, using tkinter.
Home-page: https://www.github.com/Square789/Demomgr
Author: Square789
License: UNKNOWN
Platform: UNKNOWN
Classifier: Topic :: Desktop Environment :: File Managers
Classifier: Programming Language :: Python
Classifier: Programming Language :: Tcl
Classifier: License :: OSI Approved :: MIT License
Classifier: Intended Audience :: End Users/Desktop
Requires-Dist: multiframe-list ==4.0.1
Requires-Dist: regex
Requires-Dist: schema
Requires-Dist: vdf
